setup.py
matiCalpackagetnguyen4/__init__.py
matiCalpackagetnguyen4/add.py
matiCalpackagetnguyen4/subtract.py
matiCalpackagetnguyen4.egg-info/PKG-INFO
matiCalpackagetnguyen4.egg-info/SOURCES.txt
matiCalpackagetnguyen4.egg-info/dependency_links.txt
matiCalpackagetnguyen4.egg-info/top_level.txt
matiCalpackagetnguyen4/extras/__init__.py
matiCalpackagetnguyen4/extras/divide.py
matiCalpackagetnguyen4/extras/multiply.py